nates/__init__.py
nates/config.py
nates/configuration.py
nates/do.py
nates/registry.py
nates/cli/__init__.py
nates/cli/build.py
nates/cli/configure.py
nates/cli/format.py
nates/cli/reset_env.py
nates/cli/test.py
nates/utils/__init__.py
nates/utils/utils.py
nates-0.1.3.dist-info/METADATA
nates-0.1.3.dist-info/WHEEL
nates-0.1.3.dist-info/entry_points.txt
nates-0.1.3.dist-info/RECORD
