Metadata-Version: 2.4
Name: nates
Version: 0.1.3
Author: Nathan Dahlberg
Requires-Python: >=3.11
Requires-Dist: build>=1.0.0
Requires-Dist: click>=8.0.0
Requires-Dist: paramiko>=3.5.1
Requires-Dist: pytest-cov>=4.0
Requires-Dist: pytest>=7.0
Requires-Dist: python-dotenv>=1.0.0
Requires-Dist: requests>=2.32.3
Requires-Dist: ruff>=0.9.10
Requires-Dist: simplejson>=3.19.3
Requires-Dist: tomli-w>=1.2.0
Requires-Dist: tomli>=2.2.1
Requires-Dist: twine>=4.0.0
